psgtf/__init__.py
psgtf/psgtf.py
psgtf/models/PlaystationGame.py
psgtf/models/__init__.py
ps_gametitlefinder-0.2.2.dist-info/LICENSE
ps_gametitlefinder-0.2.2.dist-info/METADATA
ps_gametitlefinder-0.2.2.dist-info/WHEEL
ps_gametitlefinder-0.2.2.dist-info/top_level.txt
ps_gametitlefinder-0.2.2.dist-info/RECORD
