Metadata-Version: 2.1
Name: ps-gametitlefinder
Version: 0.2.2
Summary: A small tool that finds Playstation game titles given a game id
Home-page: https://github.com/vladventura/ps_gametitlefinder
Author: Vladimir Ventura
Author-email: vladventura@outlook.es
Project-URL: Bug Tracker, https://github.com/vladventura/ps_gametitlefinder/issues
Classifier: Programming Language :: Python :: 3
Classifier: License :: OSI Approved :: MIT License
Classifier: Operating System :: OS Independent
Classifier: Topic :: Games/Entertainment
Classifier: Topic :: Software Development :: Libraries :: Python Modules
Classifier: Intended Audience :: Developers
Requires-Python: >=3.6
License-File: LICENSE
Requires-Dist: pandas (==1.4.2)
Requires-Dist: requests (==2.28.0)
